palmotif/__init__.py
palmotif/aacolors.py
palmotif/compute_logo.py
palmotif/mpl_plot.py
palmotif/svg_alphabet.py
palmotif/svg_logo.py
palmotif/tests/__init__.py
palmotif/tests/sequences.py
palmotif/tests/test_compute.py
palmotif/tests/test_plot.py
palmotif-0.4.dist-info/LICENSE
palmotif-0.4.dist-info/METADATA
palmotif-0.4.dist-info/WHEEL
palmotif-0.4.dist-info/top_level.txt
palmotif-0.4.dist-info/RECORD
