Metadata-Version: 2.1
Name: palmotif
Version: 0.4
Summary: Python package for computing and plotting sequence logos, with output as SVG or matplotlib
Home-page: https://github.com/agartland/palmotif
Author: Andrew Fiore-Gartland
Author-email: agartlan@fredhutch.org
Maintainer: Andrew Fiore-Gartland
Maintainer-email: agartlan@fredhutch.org
License: MIT
Platform: UNKNOWN
Requires-Dist: matplotlib
Requires-Dist: numpy (>=1.16)
Requires-Dist: pandas (>=0.24.2)
Requires-Dist: parasail (>=1.1.17)
Requires-Dist: svgwrite
Requires-Dist: scipy (>=1.4.1)
